{"metadata": {"dbt_schema_version": "https://schemas.getdbt.com/dbt/run-results/v5.json", "dbt_version": "1.7.4", "generated_at": "2024-07-23T04:34:46.652469Z", "invocation_id": "b4d1a87d-ad6e-4a18-ac87-77c9b4ba5f8c", "env": {}}, "results": [], "elapsed_time": 0.0, "args": {"profiles_dir": "/Users/altamashqureshi/Develop/dbt-certification-project", "enable_legacy_logger": false, "write_json": true, "log_format": "default", "log_path": "/Users/altamashqureshi/Develop/dbt-certification-project/logs", "partial_parse_file_diff": true, "static_parser": true, "printer_width": 80, "invocation_command": "dbt compile", "introspect": true, "strict_mode": false, "output": "text", "show_resource_report": false, "log_level": "info", "macro_debugging": false, "version_check": true, "cache_selected_only": false, "defer": false, "which": "compile", "quiet": false, "warn_error_options": {"include": [], "exclude": []}, "log_format_file": "debug", "print": true, "select": [], "use_colors_file": true, "favor_state": false, "indirect_selection": "eager", "log_file_max_bytes": 10485760, "use_colors": true, "vars": {}, "inject_ephemeral_ctes": true, "project_dir": "/Users/altamashqureshi/Develop/dbt-certification-project", "populate_cache": true, "exclude": [], "partial_parse": true, "send_anonymous_usage_stats": true, "log_level_file": "debug"}}